heroui/__init__.py
src/alert/__init__.py
src/alert/alert.py
src/alert/py.typed
src/avatar/__init__.py
src/avatar/avatar.py
src/avatar/py.typed
src/badge/__init__.py
src/badge/badge.py
src/button/__init__.py
src/button/button.py
src/button/py.typed
src/card/__init__.py
src/card/card.py
src/card/py.typed
src/checkbox/__init__.py
src/checkbox/checkbox.py
src/checkbox/py.typed
src/chip/__init__.py
src/chip/chip.py
src/code/__init__.py
src/code/code.py
src/image/__init__.py
src/image/image.py
src/input/__init__.py
src/input/input.py
src/input/py.typed
src/provider/__init__.py
src/provider/provider.py
src/provider/py.typed
src/provider/types.py
src/radio/__init__.py
src/radio/py.typed
src/radio/radio.py
src/snippet/__init__.py
src/snippet/snippet.py
src/spacer/__init__.py
src/spacer/spacer.py
src/spinner/__init__.py
src/spinner/spinner.py
src/switch/__init__.py
src/switch/switch.py
src/textarea/__init__.py
src/textarea/textarea.py
heroui_provider-0.1.5.dist-info/METADATA
heroui_provider-0.1.5.dist-info/WHEEL
heroui_provider-0.1.5.dist-info/entry_points.txt
heroui_provider-0.1.5.dist-info/licenses/LICENSE
heroui_provider-0.1.5.dist-info/RECORD
