Metadata-Version: 2.4
Name: heroui-provider
Version: 0.1.5
Summary: Hero UI - Modern UI components for Reflex Web Framework
Project-URL: Homepage, https://github.com/adarshgm/heroui
Project-URL: Bug Tracker, https://github.com/adarshgm/heroui/issues
Author-email: Adarsh Gourab Mahalik <gourabmahalikadarsh@gmail.com>
License-File: LICENSE
Classifier: License :: OSI Approved :: MIT License
Classifier: Operating System :: OS Independent
Classifier: Programming Language :: Python :: 3
Classifier: Programming Language :: Python :: 3.10
Classifier: Programming Language :: Python :: 3.11
Classifier: Programming Language :: Python :: 3.12
Classifier: Programming Language :: Python :: 3.13
Requires-Python: >=3.10
Requires-Dist: reflex>=0.7.14
Provides-Extra: all
Requires-Dist: reflex>=0.7.14; extra == 'all'
Provides-Extra: dev
Requires-Dist: black>=25.1.0; extra == 'dev'
Requires-Dist: mypy>=1.16.0; extra == 'dev'
Requires-Dist: pytest>=8.4.0; extra == 'dev'
Requires-Dist: uv>=0.7.12; extra == 'dev'
